{"config": {"view": {"width": 400, "height": 300}, "mark": {"tooltip": null}}, "hconcat": [{"mark": {"type": "bar", "align": "left", "baseline": "middle"}, "encoding": {"color": {"type": "nominal", "field": "Genre"}, "tooltip": [{"type": "quantitative", "field": "Ad Revenue(year)"}], "x": {"type": "nominal", "field": "Genre"}, "y": {"type": "quantitative", "field": "Ad Revenue(year)"}}}, {"mark": {"type": "bar", "align": "left", "baseline": "middle"}, "encoding": {"color": {"type": "nominal", "field": "Genre"}, "tooltip": [{"type": "quantitative", "field": "Sale Revenue(avg)"}], "x": {"type": "nominal", "field": "Genre"}, "y": {"type": "quantitative", "field": "Sale Revenue(avg)"}}}, {"mark": {"type": "bar", "align": "left", "baseline": "middle"}, "encoding": {"color": {"type": "nominal", "field": "Genre"}, "tooltip": [{"type": "quantitative", "field": "Average Revenue"}], "x": {"type": "nominal", "field": "Genre"}, "y": {"type": "quantitative", "field": "Average Revenue"}}}], "data": {"name": "data-5aae4074535593bd9bac5033528aa542"}, "$schema": "https://vega.github.io/schema/vega-lite/v3.4.0.json", "datasets": {"data-5aae4074535593bd9bac5033528aa542": [{"Genre": "Action", "Ad Revenue(avg)": 6315.0, "Ad Revenue(year)": 1263000, "Sale Revenue(avg)": 705963.0, "Average Revenue": 1969013.0, "Total Revenue": 29535199, "count": 15, "precent": "15%", "Average User Rating": 4.43}, {"Genre": "Adventure", "Ad Revenue(avg)": 7883.8, "Ad Revenue(year)": 1576760, "Sale Revenue(avg)": 163896.0, "Average Revenue": 1740658.0, "Total Revenue": 10443960, "count": 6, "precent": "5%", "Average User Rating": 4.25}, {"Genre": "Board", "Ad Revenue(avg)": 1567.1, "Ad Revenue(year)": 313420, "Sale Revenue(avg)": 836669.1, "Average Revenue": 1150093.0, "Total Revenue": 13801117, "count": 12, "precent": "12%", "Average User Rating": 4.0}, {"Genre": "Casual", "Ad Revenue(avg)": 2955.0, "Ad Revenue(year)": 591000, "Sale Revenue(avg)": 130155.0, "Average Revenue": 721150.5, "Total Revenue": 1442301, "count": 2, "precent": "2%", "Average User Rating": 4.5}, {"Genre": "Entertainment", "Ad Revenue(avg)": 4894.0, "Ad Revenue(year)": 978800, "Sale Revenue(avg)": 317791.0, "Average Revenue": 1296747.0, "Total Revenue": 23341461, "count": 18, "precent": "18%", "Average User Rating": 3.81}, {"Genre": "Family", "Ad Revenue(avg)": 4588.0, "Ad Revenue(year)": 917600, "Sale Revenue(avg)": 373840.0, "Average Revenue": 1291453.0, "Total Revenue": 7748719, "count": 6, "precent": "6%", "Average User Rating": 4.17}, {"Genre": "Puzzle", "Ad Revenue(avg)": 10233.4, "Ad Revenue(year)": 2046680, "Sale Revenue(avg)": 0.0, "Average Revenue": 2046688.0, "Total Revenue": 12280128, "count": 6, "precent": "6%", "Average User Rating": 3.67}, {"Genre": "Simulation", "Ad Revenue(avg)": 5677.0, "Ad Revenue(year)": 1135400, "Sale Revenue(avg)": 46867.0, "Average Revenue": 1182292.0, "Total Revenue": 13005213, "count": 11, "precent": "11%", "Average User Rating": 4.0}, {"Genre": "Strategy", "Ad Revenue(avg)": 14211.0, "Ad Revenue(year)": 2842200, "Sale Revenue(avg)": 643768.0, "Average Revenue": 3486120.0, "Total Revenue": 83666892, "count": 24, "precent": "24%", "Average User Rating": 3.81}]}}